{
  "annotations": {
    "list": [
      {
        "builtIn": 1,
        "datasource": {
          "type": "grafana",
          "uid": "-- Grafana --"
        },
        "enable": true,
        "hide": true,
        "iconColor": "rgba(0, 211, 255, 1)",
        "name": "Annotations & Alerts",
        "target": {
          "limit": 100,
          "matchAny": false,
          "tags": [],
          "type": "dashboard"
        },
        "type": "dashboard"
      }
    ]
  },
  "editable": true,
  "fiscalYearStartMonth": 0,
  "graphTooltip": 0,
  "id": 2,
  "links": [],
  "liveNow": false,
  "panels": [
    {
      "collapsed": false,
      "gridPos": {
        "h": 1,
        "w": 24,
        "x": 0,
        "y": 0
      },
      "id": 17,
      "panels": [],
      "title": "Summary",
      "type": "row"
    },
    {
      "datasource": {
        "type": "prometheus",
        "uid": "nhost"
      },
      "fieldConfig": {
        "defaults": {
          "color": {
            "mode": "thresholds"
          },
          "mappings": [],
          "thresholds": {
            "mode": "absolute",
            "steps": [
              {
                "color": "green",
                "value": null
              }
            ]
          },
          "unit": "none"
        },
        "overrides": []
      },
      "gridPos": {
        "h": 8,
        "w": 8,
        "x": 0,
        "y": 1
      },
      "id": 13,
      "options": {
        "colorMode": "value",
        "graphMode": "area",
        "justifyMode": "auto",
        "orientation": "auto",
        "reduceOptions": {
          "calcs": [
            "lastNotNull"
          ],
          "fields": "",
          "values": false
        },
        "textMode": "auto"
      },
      "pluginVersion": "9.2.0",
      "targets": [
        {
          "datasource": {
            "type": "prometheus",
            "uid": "nhost"
          },
          "editorMode": "code",
          "exemplar": false,
          "expr": "ceil(sum(increase(functions_requests_total{method=~\"$method\",route=~\"$route\"}[$__range])))",
          "instant": true,
          "legendFormat": "__auto",
          "range": false,
          "refId": "A"
        }
      ],
      "title": "Total Number of Invocations",
      "type": "stat"
    },
    {
      "datasource": {
        "type": "prometheus",
        "uid": "nhost"
      },
      "fieldConfig": {
        "defaults": {
          "color": {
            "mode": "thresholds"
          },
          "mappings": [],
          "thresholds": {
            "mode": "absolute",
            "steps": [
              {
                "color": "green",
                "value": null
              }
            ]
          },
          "unit": "decbytes"
        },
        "overrides": []
      },
      "gridPos": {
        "h": 8,
        "w": 8,
        "x": 8,
        "y": 1
      },
      "id": 14,
      "options": {
        "colorMode": "value",
        "graphMode": "area",
        "justifyMode": "auto",
        "orientation": "auto",
        "reduceOptions": {
          "calcs": [
            "lastNotNull"
          ],
          "fields": "",
          "values": false
        },
        "textMode": "auto"
      },
      "pluginVersion": "9.2.0",
      "targets": [
        {
          "datasource": {
            "type": "prometheus",
            "uid": "nhost"
          },
          "editorMode": "code",
          "exemplar": false,
          "expr": "ceil(sum(increase(functions_bytes_sent{method=~\"$method\",route=~\"$route\"}[$__range])))",
          "instant": true,
          "legendFormat": "__auto",
          "range": false,
          "refId": "A"
        }
      ],
      "title": "Total Bytes Sent",
      "type": "stat"
    },
    {
      "datasource": {
        "type": "prometheus",
        "uid": "nhost"
      },
      "fieldConfig": {
        "defaults": {
          "color": {
            "mode": "thresholds"
          },
          "mappings": [],
          "thresholds": {
            "mode": "absolute",
            "steps": [
              {
                "color": "green",
                "value": null
              }
            ]
          },
          "unit": "s"
        },
        "overrides": []
      },
      "gridPos": {
        "h": 8,
        "w": 8,
        "x": 16,
        "y": 1
      },
      "id": 15,
      "options": {
        "colorMode": "value",
        "graphMode": "area",
        "justifyMode": "auto",
        "orientation": "auto",
        "reduceOptions": {
          "calcs": [
            "lastNotNull"
          ],
          "fields": "",
          "values": false
        },
        "textMode": "auto"
      },
      "pluginVersion": "9.2.0",
      "targets": [
        {
          "datasource": {
            "type": "prometheus",
            "uid": "nhost"
          },
          "editorMode": "code",
          "exemplar": false,
          "expr": "ceil(sum(increase(functions_duration_seconds_sum{method=~\"$method\",route=~\"$route\"}[$__range])))",
          "instant": true,
          "legendFormat": "__auto",
          "range": false,
          "refId": "A"
        }
      ],
      "title": "Total Duration",
      "type": "stat"
    },
    {
      "collapsed": false,
      "gridPos": {
        "h": 1,
        "w": 24,
        "x": 0,
        "y": 9
      },
      "id": 6,
      "panels": [],
      "title": "General",
      "type": "row"
    },
    {
      "datasource": {
        "type": "prometheus",
        "uid": "nhost"
      },
      "description": "Number of invocations by method/function",
      "fieldConfig": {
        "defaults": {
          "color": {
            "mode": "palette-classic"
          },
          "custom": {
            "axisCenteredZero": false,
            "axisColorMode": "text",
            "axisLabel": "",
            "axisPlacement": "auto",
            "barAlignment": 0,
            "drawStyle": "line",
            "fillOpacity": 0,
            "gradientMode": "none",
            "hideFrom": {
              "legend": false,
              "tooltip": false,
              "viz": false
            },
            "lineInterpolation": "linear",
            "lineWidth": 1,
            "pointSize": 5,
            "scaleDistribution": {
              "type": "linear"
            },
            "showPoints": "auto",
            "spanNulls": false,
            "stacking": {
              "group": "A",
              "mode": "none"
            },
            "thresholdsStyle": {
              "mode": "off"
            }
          },
          "mappings": [],
          "thresholds": {
            "mode": "absolute",
            "steps": [
              {
                "color": "green",
                "value": null
              },
              {
                "color": "red",
                "value": 80
              }
            ]
          }
        },
        "overrides": []
      },
      "gridPos": {
        "h": 8,
        "w": 12,
        "x": 0,
        "y": 10
      },
      "id": 2,
      "options": {
        "legend": {
          "calcs": [],
          "displayMode": "list",
          "placement": "bottom",
          "showLegend": true
        },
        "tooltip": {
          "mode": "single",
          "sort": "none"
        }
      },
      "targets": [
        {
          "datasource": {
            "type": "prometheus",
            "uid": "nhost"
          },
          "editorMode": "code",
          "expr": "sum by(method, route) (increase(functions_requests_total{method=~\"$method\",route=~\"$route\"}[$__rate_interval]))",
          "format": "time_series",
          "interval": "2m",
          "legendFormat": "{{ print "{{ method }} - {{ route }}" }}",
          "range": true,
          "refId": "A"
        }
      ],
      "title": "Invocations",
      "type": "timeseries"
    },
    {
      "datasource": {
        "type": "prometheus",
        "uid": "nhost"
      },
      "description": "Number of invocations by status response",
      "fieldConfig": {
        "defaults": {
          "color": {
            "mode": "palette-classic"
          },
          "custom": {
            "axisCenteredZero": false,
            "axisColorMode": "text",
            "axisLabel": "",
            "axisPlacement": "auto",
            "barAlignment": 0,
            "drawStyle": "line",
            "fillOpacity": 0,
            "gradientMode": "none",
            "hideFrom": {
              "legend": false,
              "tooltip": false,
              "viz": false
            },
            "lineInterpolation": "linear",
            "lineWidth": 1,
            "pointSize": 5,
            "scaleDistribution": {
              "type": "linear"
            },
            "showPoints": "auto",
            "spanNulls": false,
            "stacking": {
              "group": "A",
              "mode": "none"
            },
            "thresholdsStyle": {
              "mode": "off"
            }
          },
          "mappings": [],
          "thresholds": {
            "mode": "absolute",
            "steps": [
              {
                "color": "green",
                "value": null
              },
              {
                "color": "red",
                "value": 80
              }
            ]
          }
        },
        "overrides": []
      },
      "gridPos": {
        "h": 8,
        "w": 12,
        "x": 12,
        "y": 10
      },
      "id": 21,
      "options": {
        "legend": {
          "calcs": [],
          "displayMode": "list",
          "placement": "bottom",
          "showLegend": true
        },
        "tooltip": {
          "mode": "single",
          "sort": "none"
        }
      },
      "targets": [
        {
          "datasource": {
            "type": "prometheus",
            "uid": "nhost"
          },
          "editorMode": "code",
          "expr": "sum by(status) (increase(functions_requests_total{method=~\"$method\",route=~\"$route\"}[$__rate_interval]))",
          "format": "time_series",
          "interval": "2m",
          "legendFormat": "{{ print "{{status}}" }}",
          "range": true,
          "refId": "A"
        }
      ],
      "title": "Response Status",
      "type": "timeseries"
    },
    {
      "datasource": {
        "type": "prometheus",
        "uid": "nhost"
      },
      "description": "",
      "fieldConfig": {
        "defaults": {
          "color": {
            "mode": "palette-classic"
          },
          "custom": {
            "axisCenteredZero": false,
            "axisColorMode": "text",
            "axisLabel": "",
            "axisPlacement": "auto",
            "barAlignment": 0,
            "drawStyle": "line",
            "fillOpacity": 0,
            "gradientMode": "none",
            "hideFrom": {
              "legend": false,
              "tooltip": false,
              "viz": false
            },
            "lineInterpolation": "linear",
            "lineWidth": 1,
            "pointSize": 5,
            "scaleDistribution": {
              "type": "linear"
            },
            "showPoints": "auto",
            "spanNulls": false,
            "stacking": {
              "group": "A",
              "mode": "none"
            },
            "thresholdsStyle": {
              "mode": "off"
            }
          },
          "mappings": [],
          "thresholds": {
            "mode": "absolute",
            "steps": [
              {
                "color": "green",
                "value": null
              },
              {
                "color": "red",
                "value": 80
              }
            ]
          },
          "unit": "bytes"
        },
        "overrides": []
      },
      "gridPos": {
        "h": 8,
        "w": 12,
        "x": 0,
        "y": 18
      },
      "id": 8,
      "options": {
        "legend": {
          "calcs": [],
          "displayMode": "list",
          "placement": "bottom",
          "showLegend": true
        },
        "tooltip": {
          "mode": "single",
          "sort": "none"
        }
      },
      "targets": [
        {
          "datasource": {
            "type": "prometheus",
            "uid": "nhost"
          },
          "editorMode": "code",
          "expr": "sum by(method, route) (increase(functions_bytes_sent{method=~\"$method\", route=~\"$route\"}[$__rate_interval])) / sum by(method, route) (increase(functions_requests_total{method=~\"$method\", route=~\"$route\"}[$__rate_interval]))",
          "interval": "2m",
          "legendFormat": "{{ print "{{ method }} - {{ route }}" }}",
          "range": true,
          "refId": "A"
        }
      ],
      "title": "Average Response Size",
      "type": "timeseries"
    },
    {
      "datasource": {
        "type": "prometheus",
        "uid": "nhost"
      },
      "fieldConfig": {
        "defaults": {
          "color": {
            "mode": "continuous-GrYlRd"
          },
          "custom": {
            "align": "auto",
            "displayMode": "auto",
            "filterable": true,
            "inspect": false
          },
          "mappings": [],
          "thresholds": {
            "mode": "absolute",
            "steps": [
              {
                "color": "green",
                "value": null
              }
            ]
          }
        },
        "overrides": [
          {
            "matcher": {
              "id": "byName",
              "options": "Time"
            },
            "properties": [
              {
                "id": "custom.width",
                "value": 183
              }
            ]
          }
        ]
      },
      "gridPos": {
        "h": 8,
        "w": 12,
        "x": 12,
        "y": 18
      },
      "id": 4,
      "options": {
        "footer": {
          "fields": "",
          "reducer": [
            "sum"
          ],
          "show": false
        },
        "showHeader": true,
        "sortBy": [
          {
            "desc": true,
            "displayName": "Value"
          }
        ]
      },
      "pluginVersion": "9.2.0",
      "targets": [
        {
          "datasource": {
            "type": "prometheus",
            "uid": "nhost"
          },
          "editorMode": "code",
          "exemplar": false,
          "expr": "ceil(sum by(route, method) (increase(functions_requests_total{method=~\"$method\",route=~\"$route\"}[$__range])))",
          "format": "table",
          "instant": true,
          "interval": "2m",
          "legendFormat": "{{ print "{{ method }} - {{ route }}" }}",
          "range": false,
          "refId": "A"
        }
      ],
      "title": "Total Requests",
      "transformations": [],
      "type": "table"
    },
    {
      "collapsed": false,
      "gridPos": {
        "h": 1,
        "w": 24,
        "x": 0,
        "y": 26
      },
      "id": 26,
      "panels": [],
      "title": "Response Times",
      "type": "row"
    },
    {
      "datasource": {
        "type": "prometheus",
        "uid": "nhost"
      },
      "description": "Time the slowest response took",
      "fieldConfig": {
        "defaults": {
          "color": {
            "mode": "palette-classic"
          },
          "custom": {
            "axisCenteredZero": false,
            "axisColorMode": "text",
            "axisLabel": "",
            "axisPlacement": "auto",
            "barAlignment": 0,
            "drawStyle": "line",
            "fillOpacity": 0,
            "gradientMode": "none",
            "hideFrom": {
              "legend": false,
              "tooltip": false,
              "viz": false
            },
            "lineInterpolation": "linear",
            "lineWidth": 1,
            "pointSize": 5,
            "scaleDistribution": {
              "type": "linear"
            },
            "showPoints": "auto",
            "spanNulls": false,
            "stacking": {
              "group": "A",
              "mode": "none"
            },
            "thresholdsStyle": {
              "mode": "off"
            }
          },
          "mappings": [],
          "thresholds": {
            "mode": "absolute",
            "steps": [
              {
                "color": "green"
              },
              {
                "color": "red",
                "value": 80
              }
            ]
          },
          "unit": "s"
        },
        "overrides": []
      },
      "gridPos": {
        "h": 8,
        "w": 12,
        "x": 0,
        "y": 27
      },
      "id": 24,
      "options": {
        "legend": {
          "calcs": [],
          "displayMode": "list",
          "placement": "bottom",
          "showLegend": true
        },
        "tooltip": {
          "mode": "single",
          "sort": "none"
        }
      },
      "targets": [
        {
          "datasource": {
            "type": "prometheus",
            "uid": "nhost"
          },
          "editorMode": "code",
          "expr": "histogram_quantile(1, rate(functions_duration_seconds_bucket[$__rate_interval]))",
          "interval": "2m",
          "legendFormat": "{{ print "{{ method }} - {{ route }}" }}",
          "range": true,
          "refId": "A"
        }
      ],
      "title": "Maximum Response Time",
      "type": "timeseries"
    },
    {
      "datasource": {
        "type": "prometheus",
        "uid": "nhost"
      },
      "description": "The 95th percentile of response times refers to the value below which 95% of response times fall. In other words, it is the point at which only 5% of response times are higher",
      "fieldConfig": {
        "defaults": {
          "color": {
            "mode": "palette-classic"
          },
          "custom": {
            "axisCenteredZero": false,
            "axisColorMode": "text",
            "axisLabel": "",
            "axisPlacement": "auto",
            "barAlignment": 0,
            "drawStyle": "line",
            "fillOpacity": 0,
            "gradientMode": "none",
            "hideFrom": {
              "legend": false,
              "tooltip": false,
              "viz": false
            },
            "lineInterpolation": "linear",
            "lineWidth": 1,
            "pointSize": 5,
            "scaleDistribution": {
              "type": "linear"
            },
            "showPoints": "auto",
            "spanNulls": false,
            "stacking": {
              "group": "A",
              "mode": "none"
            },
            "thresholdsStyle": {
              "mode": "off"
            }
          },
          "mappings": [],
          "thresholds": {
            "mode": "absolute",
            "steps": [
              {
                "color": "green"
              },
              {
                "color": "red",
                "value": 80
              }
            ]
          },
          "unit": "s"
        },
        "overrides": []
      },
      "gridPos": {
        "h": 8,
        "w": 12,
        "x": 12,
        "y": 27
      },
      "id": 22,
      "options": {
        "legend": {
          "calcs": [],
          "displayMode": "list",
          "placement": "bottom",
          "showLegend": true
        },
        "tooltip": {
          "mode": "single",
          "sort": "none"
        }
      },
      "targets": [
        {
          "datasource": {
            "type": "prometheus",
            "uid": "nhost"
          },
          "editorMode": "code",
          "expr": "histogram_quantile(0.95, rate(functions_duration_seconds_bucket[$__rate_interval]))",
          "interval": "2m",
          "legendFormat": "{{ print "{{ method }} - {{ route }}" }}",
          "range": true,
          "refId": "A"
        }
      ],
      "title": "Response times 95th percentile",
      "type": "timeseries"
    },
    {
      "datasource": {
        "type": "prometheus",
        "uid": "nhost"
      },
      "description": "The 75th percentile of response times refers to the value below which 75% of response times fall. In other words, it is the point at which 25% of response times are higher",
      "fieldConfig": {
        "defaults": {
          "color": {
            "mode": "palette-classic"
          },
          "custom": {
            "axisCenteredZero": false,
            "axisColorMode": "text",
            "axisLabel": "",
            "axisPlacement": "auto",
            "barAlignment": 0,
            "drawStyle": "line",
            "fillOpacity": 0,
            "gradientMode": "none",
            "hideFrom": {
              "legend": false,
              "tooltip": false,
              "viz": false
            },
            "lineInterpolation": "linear",
            "lineWidth": 1,
            "pointSize": 5,
            "scaleDistribution": {
              "type": "linear"
            },
            "showPoints": "auto",
            "spanNulls": false,
            "stacking": {
              "group": "A",
              "mode": "none"
            },
            "thresholdsStyle": {
              "mode": "off"
            }
          },
          "mappings": [],
          "thresholds": {
            "mode": "absolute",
            "steps": [
              {
                "color": "green"
              },
              {
                "color": "red",
                "value": 80
              }
            ]
          },
          "unit": "s"
        },
        "overrides": []
      },
      "gridPos": {
        "h": 8,
        "w": 12,
        "x": 0,
        "y": 35
      },
      "id": 23,
      "options": {
        "legend": {
          "calcs": [],
          "displayMode": "list",
          "placement": "bottom",
          "showLegend": true
        },
        "tooltip": {
          "mode": "single",
          "sort": "none"
        }
      },
      "targets": [
        {
          "datasource": {
            "type": "prometheus",
            "uid": "nhost"
          },
          "editorMode": "code",
          "expr": "histogram_quantile(0.75, rate(functions_duration_seconds_bucket[$__rate_interval]))",
          "interval": "2m",
          "legendFormat": "{{ print "{{ method }} - {{ route }}" }}",
          "range": true,
          "refId": "A"
        }
      ],
      "title": "Response times 75th percentile",
      "type": "timeseries"
    },
    {
      "datasource": {
        "type": "prometheus",
        "uid": "nhost"
      },
      "description": "",
      "fieldConfig": {
        "defaults": {
          "color": {
            "mode": "palette-classic"
          },
          "custom": {
            "axisCenteredZero": false,
            "axisColorMode": "text",
            "axisLabel": "",
            "axisPlacement": "auto",
            "barAlignment": 0,
            "drawStyle": "line",
            "fillOpacity": 0,
            "gradientMode": "none",
            "hideFrom": {
              "legend": false,
              "tooltip": false,
              "viz": false
            },
            "lineInterpolation": "linear",
            "lineWidth": 1,
            "pointSize": 5,
            "scaleDistribution": {
              "type": "linear"
            },
            "showPoints": "auto",
            "spanNulls": false,
            "stacking": {
              "group": "A",
              "mode": "none"
            },
            "thresholdsStyle": {
              "mode": "off"
            }
          },
          "mappings": [],
          "thresholds": {
            "mode": "absolute",
            "steps": [
              {
                "color": "green"
              },
              {
                "color": "red",
                "value": 80
              }
            ]
          },
          "unit": "s"
        },
        "overrides": []
      },
      "gridPos": {
        "h": 8,
        "w": 12,
        "x": 12,
        "y": 35
      },
      "id": 11,
      "options": {
        "legend": {
          "calcs": [],
          "displayMode": "list",
          "placement": "bottom",
          "showLegend": true
        },
        "tooltip": {
          "mode": "single",
          "sort": "none"
        }
      },
      "targets": [
        {
          "datasource": {
            "type": "prometheus",
            "uid": "nhost"
          },
          "editorMode": "builder",
          "expr": "sum by(method, route) (increase(functions_duration_seconds_sum{method=~\"$method\", route=~\"$route\"}[$__rate_interval])) / sum by(method, route) (increase(functions_duration_seconds_count{method=~\"$method\", route=~\"$route\"}[$__rate_interval]))",
          "interval": "2m",
          "legendFormat": "{{ print "{{ method }} - {{ route }}" }}",
          "range": true,
          "refId": "A"
        }
      ],
      "title": "Average Response Time",
      "type": "timeseries"
    },
    {
      "collapsed": false,
      "gridPos": {
        "h": 1,
        "w": 24,
        "x": 0,
        "y": 43
      },
      "id": 19,
      "panels": [],
      "title": "Errors",
      "type": "row"
    },
    {
      "datasource": {
        "type": "prometheus",
        "uid": "nhost"
      },
      "description": "Number of invocations that failed divided by the total number of invocations",
      "fieldConfig": {
        "defaults": {
          "color": {
            "mode": "palette-classic"
          },
          "custom": {
            "axisCenteredZero": false,
            "axisColorMode": "text",
            "axisLabel": "",
            "axisPlacement": "auto",
            "barAlignment": 0,
            "drawStyle": "line",
            "fillOpacity": 0,
            "gradientMode": "none",
            "hideFrom": {
              "legend": false,
              "tooltip": false,
              "viz": false
            },
            "lineInterpolation": "linear",
            "lineWidth": 1,
            "pointSize": 5,
            "scaleDistribution": {
              "type": "linear"
            },
            "showPoints": "auto",
            "spanNulls": false,
            "stacking": {
              "group": "A",
              "mode": "none"
            },
            "thresholdsStyle": {
              "mode": "off"
            }
          },
          "mappings": [],
          "thresholds": {
            "mode": "absolute",
            "steps": [
              {
                "color": "green"
              },
              {
                "color": "red",
                "value": 80
              }
            ]
          },
          "unit": "percentunit"
        },
        "overrides": []
      },
      "gridPos": {
        "h": 8,
        "w": 12,
        "x": 0,
        "y": 44
      },
      "id": 20,
      "options": {
        "legend": {
          "calcs": [],
          "displayMode": "list",
          "placement": "bottom",
          "showLegend": true
        },
        "tooltip": {
          "mode": "single",
          "sort": "none"
        }
      },
      "targets": [
        {
          "datasource": {
            "type": "prometheus",
            "uid": "nhost"
          },
          "editorMode": "code",
          "expr": "sum by(method, route) (increase(functions_requests_total{method=~\"$method\",route=~\"$route\",status=~\"^[4-5].*\"}[$__rate_interval])) / sum by(method, route) (increase(functions_requests_total[$__rate_interval]))",
          "format": "time_series",
          "interval": "2m",
          "legendFormat": "{{ print "{{ method }} - {{ route }}" }}",
          "range": true,
          "refId": "A"
        }
      ],
      "title": "Error Rate",
      "type": "timeseries"
    },
    {
      "datasource": {
        "type": "prometheus",
        "uid": "nhost"
      },
      "fieldConfig": {
        "defaults": {
          "color": {
            "mode": "continuous-GrYlRd"
          },
          "custom": {
            "align": "auto",
            "displayMode": "auto",
            "filterable": true,
            "inspect": false
          },
          "mappings": [],
          "thresholds": {
            "mode": "absolute",
            "steps": [
              {
                "color": "green"
              }
            ]
          }
        },
        "overrides": [
          {
            "matcher": {
              "id": "byName",
              "options": "Time"
            },
            "properties": [
              {
                "id": "custom.width",
                "value": 183
              }
            ]
          }
        ]
      },
      "gridPos": {
        "h": 8,
        "w": 12,
        "x": 12,
        "y": 44
      },
      "id": 10,
      "options": {
        "footer": {
          "fields": "",
          "reducer": [
            "sum"
          ],
          "show": false
        },
        "showHeader": true,
        "sortBy": [
          {
            "desc": true,
            "displayName": "Value"
          }
        ]
      },
      "pluginVersion": "9.2.0",
      "targets": [
        {
          "datasource": {
            "type": "prometheus",
            "uid": "nhost"
          },
          "editorMode": "code",
          "exemplar": false,
          "expr": "ceil(sum by(route, method,status) (increase(functions_requests_total{method=~\"$method\",route=~\"$route\",status=~\"^[4-5].*\"}[$__range])))",
          "format": "table",
          "instant": true,
          "interval": "2m",
          "legendFormat": "{{ print "{{ method }} - {{ route }}" }}",
          "range": false,
          "refId": "A"
        }
      ],
      "title": "Total Errors",
      "transformations": [],
      "type": "table"
    }
  ],
  "refresh": false,
  "schemaVersion": 37,
  "style": "dark",
  "tags": [
    "nhost"
  ],
  "templating": {
    "list": [
      {
        "allValue": "",
        "current": {
          "selected": false,
          "text": "All",
          "value": "$__all"
        },
        "datasource": {
          "type": "prometheus",
          "uid": "nhost"
        },
        "definition": "label_values(functions_requests_total, method)",
        "hide": 0,
        "includeAll": true,
        "multi": false,
        "name": "method",
        "options": [],
        "query": {
          "query": "label_values(functions_requests_total, method)",
          "refId": "StandardVariableQuery"
        },
        "refresh": 1,
        "regex": "",
        "skipUrlSync": false,
        "sort": 0,
        "type": "query"
      },
      {
        "allValue": ".*",
        "current": {
          "selected": false,
          "text": "All",
          "value": "$__all"
        },
        "datasource": {
          "type": "prometheus",
          "uid": "nhost"
        },
        "definition": "label_values(functions_requests_total, route)",
        "hide": 0,
        "includeAll": true,
        "multi": false,
        "name": "route",
        "options": [],
        "query": {
          "query": "label_values(functions_requests_total, route)",
          "refId": "StandardVariableQuery"
        },
        "refresh": 1,
        "regex": "",
        "skipUrlSync": false,
        "sort": 0,
        "type": "query"
      }
    ]
  },
  "time": {
    "from": "now-6h",
    "to": "now"
  },
  "timepicker": {},
  "timezone": "",
  "title": "Functions Metrics",
  "uid": "86rT7vQ4k",
  "version": 6,
  "weekStart": ""
}
